mdtocf/__init__.py
mdtocf/mdtocf.py
mdtocf/classes/ConfluencePublisher.py
mdtocf/classes/ConfluenceRenderer.py
mdtocf/classes/KeyValue.py
mdtocf/classes/MetadataPlugin.py
mdtocf-1.2.7.dist-info/licenses/LICENSE
mdtocf-1.2.7.dist-info/METADATA
mdtocf-1.2.7.dist-info/WHEEL
mdtocf-1.2.7.dist-info/entry_points.txt
mdtocf-1.2.7.dist-info/top_level.txt
mdtocf-1.2.7.dist-info/RECORD
