Metadata-Version: 2.4
Name: mdtocf
Version: 1.2.7
Summary: Markdown files/directory publishing to Atlassian Confluence
Author-email: Olaf Reitmaier Veracierta <olafrv@gmail.com>
License-Expression: MIT
Project-URL: Homepage, https://github.com/olafrv/mdtocf
Project-URL: Repository, https://github.com/olafrv/mdtocf
Project-URL: Issues, https://github.com/olafrv/mdtocf/issues
Keywords: markdown,confluence,atlassian,publish,mdtocf
Classifier: Programming Language :: Python :: 3
Classifier: Programming Language :: Python :: 3.12
Classifier: Operating System :: OS Independent
Requires-Python: >=3.12
License-File: LICENSE
Requires-Dist: mistune==3.1.3
Requires-Dist: pickleDB==1.3.2
Requires-Dist: atlassian-python-api==4.0.4
Provides-Extra: dev
Requires-Dist: black; extra == "dev"
Requires-Dist: pytest; extra == "dev"
Requires-Dist: build; extra == "dev"
Requires-Dist: twine; extra == "dev"
Dynamic: license-file
